dolivroo/__init__.py
dolivroo/client.py
dolivroo/exceptions.py
dolivroo/http_client.py
dolivroo/resources.py
dolivroo-1.0.0.dist-info/METADATA
dolivroo-1.0.0.dist-info/WHEEL
dolivroo-1.0.0.dist-info/top_level.txt
dolivroo-1.0.0.dist-info/RECORD
