Metadata-Version: 2.4
Name: dolivroo
Version: 1.0.0
Summary: Official Dolivroo SDK for Python - Unified shipping API for Algeria
Author-email: Dolivroo <support@dolivroo.com>
License: MIT
Project-URL: Homepage, https://dolivroo.com
Project-URL: Documentation, https://dolivroo.com/dashboard/docs
Project-URL: Repository, https://github.com/dolivroo/sdk-python
Keywords: dolivroo,shipping,delivery,algeria,yalidine,ecotrack,api
Classifier: Development Status :: 5 - Production/Stable
Classifier: Intended Audience :: Developers
Classifier: License :: OSI Approved :: MIT License
Classifier: Operating System :: OS Independent
Classifier: Programming Language :: Python :: 3
Classifier: Programming Language :: Python :: 3.8
Classifier: Programming Language :: Python :: 3.9
Classifier: Programming Language :: Python :: 3.10
Classifier: Programming Language :: Python :: 3.11
Classifier: Programming Language :: Python :: 3.12
Classifier: Topic :: Software Development :: Libraries :: Python Modules
Requires-Python: >=3.8
Requires-Dist: requests>=2.25.0
Requires-Dist: typing-extensions>=4.0.0
Provides-Extra: dev
Requires-Dist: pytest>=7.0.0; extra == "dev"
Requires-Dist: pytest-asyncio>=0.21.0; extra == "dev"
Requires-Dist: black>=23.0.0; extra == "dev"
Requires-Dist: mypy>=1.0.0; extra == "dev"
Requires-Dist: types-requests>=2.31.0; extra == "dev"
